lackey_mcp_sidecar/__init__.py
lackey_mcp_sidecar/main.py
lackey_mcp_sidecar/static/taskitty_white_check.png
lackey_mcp_sidecar/static/css/animations.css
lackey_mcp_sidecar/static/css/base.css
lackey_mcp_sidecar/static/css/components.css
lackey_mcp_sidecar/static/css/dashboard.css
lackey_mcp_sidecar/static/css/main.css
lackey_mcp_sidecar/static/css/task-graph.css
lackey_mcp_sidecar/static/js/app.js
lackey_mcp_sidecar/static/js/dashboard.js
lackey_mcp_sidecar/static/js/main.js
lackey_mcp_sidecar/static/js/projects.js
lackey_mcp_sidecar/static/js/search.js
lackey_mcp_sidecar/static/js/task-graph.js
lackey_mcp_sidecar/static/js/ui-utils.js
lackey_mcp_sidecar/templates/index.html
lackey_mcp_sidecar-1.0.2.dist-info/licenses/LICENSE
lackey_mcp_sidecar-1.0.2.dist-info/METADATA
lackey_mcp_sidecar-1.0.2.dist-info/WHEEL
lackey_mcp_sidecar-1.0.2.dist-info/entry_points.txt
lackey_mcp_sidecar-1.0.2.dist-info/top_level.txt
lackey_mcp_sidecar-1.0.2.dist-info/RECORD
