Metadata-Version: 2.4
Name: lackey-mcp-sidecar
Version: 1.0.2
Summary: FastAPI web interface for Lackey task management via MCP
Author: Lackey Community
License-Expression: MIT
Project-URL: Source, https://github.com/lackey-project/lackey-sidecar
Requires-Python: >=3.8
License-File: LICENSE
Requires-Dist: fastapi==0.104.1
Requires-Dist: uvicorn[standard]==0.24.0
Requires-Dist: pydantic==2.5.0
Requires-Dist: networkx
Requires-Dist: PyYAML
Requires-Dist: jinja2
Requires-Dist: watchdog
Dynamic: license-file
